[
  {
    "sku": "PMD-SS-25",
    "name": "PANELED MINI DRESS",
    "mrp": 10000.0,
    "color": "black",
    "fabric": "MILL DEADSTOCK         5 OUNCE 100% COTTON DENIM",
    "description": "contrast top stitch detail - front zip closure - mid thigh length - fitted on the waist - slight flare at the hem",
    "category": "one-pieces",
    "sub_category": "dress",
    "occasion": "evening, party, wedding",
    "style_vibe": "classic",
    "color_family": "monochrome",
    "silhouette": "a - line",
    "body_types": "hour glass, plus size, pear",
    "fit_note": "true-to-size",
    "pairs_with": "",
    "avoid_pairing": "",
    "styling_note": "",
    "bestseller": "",
    "season": "",
    "image_file": "",
    "has_image": false,
    "shopify_image": "PMD-SS-25_shopify.jpg",
    "shopify_url": "https://cdn.shopify.com/s/files/1/0635/1791/7437/files/ASV09165.jpg?v=1749682449&width=1946",
    "image_file_shopify": "PMD-SS-25_shopify.jpg",
    "has_shopify": true,
    "shopify_clean": "PMD-SS-25_shopify_clean.png",
    "linesheet_image": "PMD-SS-25.png",
    "linesheet_clean": "PMD-SS-25_clean.png",
    "display_url": "https://res.cloudinary.com/dptznozxq/image/upload/v1776320363/tryon/linesheet/PMD-SS-25.png",
    "clean_url": "https://res.cloudinary.com/dptznozxq/image/upload/v1776320364/tryon/linesheet_clean/PMD-SS-25_clean.png"
  },
  {
    "sku": "RPS-SS-25",
    "name": "RIPPLE SHIRT",
    "mrp": 8500.0,
    "color": "white",
    "fabric": "100% COTTON SELF WEAVE",
    "description": "notched collar - shoulder to arm ruching detail - regular cuff - high to low hem - relaxed fit",
    "category": "tops",
    "sub_category": "shirt",
    "occasion": "vacation, work",
    "style_vibe": "elegant",
    "color_family": "neutrals",
    "silhouette": "relaxed",
    "body_types": "",
    "fit_note": "true-to-size",
    "pairs_with": "",
    "avoid_pairing": "",
    "styling_note": "",
    "bestseller": "",
    "season": "",
    "image_file": "RPS-SS-25.jpg",
    "has_image": true,
    "image_file_clean": "RPS-SS-25_clean.png",
    "shopify_image": "RPS-SS-25_shopify.jpg",
    "shopify_url": "https://cdn.shopify.com/s/files/1/0635/1791/7437/files/ASV08941-3.jpg?v=1750487524&width=1946",
    "image_file_shopify": "RPS-SS-25_shopify.jpg",
    "has_shopify": true,
    "shopify_clean": "RPS-SS-25_shopify_clean.png",
    "linesheet_image": "RPS-SS-25.png",
    "linesheet_clean": "RPS-SS-25_clean.png",
    "display_url": "https://res.cloudinary.com/dptznozxq/image/upload/v1776320366/tryon/linesheet/RPS-SS-25.png",
    "clean_url": "https://res.cloudinary.com/dptznozxq/image/upload/v1776320368/tryon/linesheet_clean/RPS-SS-25_clean.png"
  },
  {
    "sku": "RVD-SS-25",
    "name": "RIVIERA DRESS",
    "mrp": 14500.0,
    "color": "cream,blue",
    "fabric": "100% COTTON WINDOWPANE CHECK WEAVE  + MILL DEADSTOCK 11 OUNCE 100% COTTON  LYCRA DENIM",
    "description": "fitted dress bodice - front and back darts - side zip closure - flared dress bottom - midi length",
    "category": "one-pieces",
    "sub_category": "dress",
    "occasion": "party, vacation, wedding",
    "style_vibe": "elegant",
    "color_family": "bright",
    "silhouette": "tailored",
    "body_types": "",
    "fit_note": "true-to-size",
    "pairs_with": "",
    "avoid_pairing": "",
    "styling_note": "",
    "bestseller": "",
    "season": "",
    "image_file": "RVD-SS-25.png",
    "has_image": true,
    "image_file_clean": "RVD-SS-25_clean.png",
    "shopify_image": "RVD-SS-25_shopify.jpg",
    "shopify_url": "https://cdn.shopify.com/s/files/1/0635/1791/7437/files/RIVIERA_DRESS.png?v=1776171610&width=1946",
    "image_file_shopify": "RVD-SS-25_shopify.jpg",
    "has_shopify": true,
    "shopify_clean": "RVD-SS-25_shopify_clean.png",
    "linesheet_image": "RVD-SS-25.png",
    "linesheet_clean": "RVD-SS-25_clean.png",
    "display_url": "https://res.cloudinary.com/dptznozxq/image/upload/v1776320371/tryon/linesheet/RVD-SS-25.png",
    "clean_url": "https://res.cloudinary.com/dptznozxq/image/upload/v1776320372/tryon/linesheet_clean/RVD-SS-25_clean.png"
  },
  {
    "sku": "SHD-SS-25",
    "name": "SAHARA DRESS",
    "mrp": 15000.0,
    "color": "blue",
    "fabric": "MILL DEADSTOCK  7.5 OUNCE    100% COTTON DENIM",
    "description": "square neck line - fabric scrap flower detail - top stitch detail - mid thigh length - flared a line fit",
    "category": "one-pieces",
    "sub_category": "dress",
    "occasion": "party, vacation, evening",
    "style_vibe": "statement",
    "color_family": "jewel",
    "silhouette": "a - line",
    "body_types": "",
    "fit_note": "true-to-size",
    "pairs_with": "",
    "avoid_pairing": "",
    "styling_note": "",
    "bestseller": "",
    "season": "",
    "image_file": "SHD-SS-25.png",
    "has_image": true,
    "image_file_clean": "SHD-SS-25_clean.png",
    "shopify_image": "SHD-SS-25_shopify.jpg",
    "shopify_url": "https://cdn.shopify.com/s/files/1/0635/1791/7437/files/ASV08361-2.jpg?v=1750769407&width=1946",
    "image_file_shopify": "SHD-SS-25_shopify.jpg",
    "has_shopify": true,
    "shopify_clean": "SHD-SS-25_shopify_clean.png",
    "linesheet_image": "SHD-SS-25.png",
    "linesheet_clean": "SHD-SS-25_clean.png",
    "display_url": "https://res.cloudinary.com/dptznozxq/image/upload/v1776320374/tryon/linesheet/SHD-SS-25.png",
    "clean_url": "https://res.cloudinary.com/dptznozxq/image/upload/v1776320375/tryon/linesheet_clean/SHD-SS-25_clean.png"
  },
  {
    "sku": "CNP-SS-25",
    "name": "CINE PANTS",
    "mrp": 12500.0,
    "color": "blue",
    "fabric": "MILL DEADSTOCK  7.5 OUNCE    100% COTTON  DENIM",
    "description": "high waisted -  circular pant leg - frayed fabric strip detail - front fly closure- front side pocket",
    "category": "bottoms",
    "sub_category": "pants",
    "occasion": "party, vacation, evening",
    "style_vibe": "statement",
    "color_family": "jewel",
    "silhouette": "tailored",
    "body_types": "",
    "fit_note": "true-to-size",
    "pairs_with": "",
    "avoid_pairing": "",
    "styling_note": "",
    "bestseller": "",
    "season": "",
    "image_file": "CNP-SS-25.png",
    "has_image": true,
    "image_file_clean": "CNP-SS-25_clean.png",
    "shopify_image": "CNP-SS-25_shopify.jpg",
    "shopify_url": "https://cdn.shopify.com/s/files/1/0635/1791/7437/files/CINE_PANTS_SS25.png?v=1776169539&width=1946",
    "image_file_shopify": "CNP-SS-25_shopify.jpg",
    "has_shopify": true,
    "shopify_clean": "CNP-SS-25_shopify_clean.png",
    "linesheet_image": "CNP-SS-25.jpg",
    "linesheet_clean": "CNP-SS-25_clean.png",
    "display_url": "https://res.cloudinary.com/dptznozxq/image/upload/v1776320376/tryon/linesheet/CNP-SS-25.jpg",
    "clean_url": "https://res.cloudinary.com/dptznozxq/image/upload/v1776320379/tryon/linesheet_clean/CNP-SS-25_clean.png"
  },
  {
    "sku": "MRS-SS-25",
    "name": "MIRAGE SHIRT",
    "mrp": 7500.0,
    "color": "cream,blue",
    "fabric": "100% COTTON WINDOWPANE CHECK WEAVE",
    "description": "open collar - padded shoulder - regular cuff - front and back pleat detail- cropped length",
    "category": "tops",
    "sub_category": "shirt",
    "occasion": "vacation, party",
    "style_vibe": "playful",
    "color_family": "neutrals",
    "silhouette": "relaxed",
    "body_types": "",
    "fit_note": "runs-large",
    "pairs_with": "",
    "avoid_pairing": "",
    "styling_note": "",
    "bestseller": "",
    "season": "",
    "image_file": "MRS-SS-25.png",
    "has_image": true,
    "image_file_clean": "MRS-SS-25_clean.png",
    "shopify_image": "MRS-SS-25_shopify.jpg",
    "shopify_url": "https://cdn.shopify.com/s/files/1/0635/1791/7437/files/ASV08728-2.jpg?v=1750495183&width=1946",
    "image_file_shopify": "MRS-SS-25_shopify.jpg",
    "has_shopify": true,
    "shopify_clean": "MRS-SS-25_shopify_clean.png",
    "linesheet_image": "MRS-SS-25.png",
    "linesheet_clean": "MRS-SS-25_clean.png",
    "display_url": "https://res.cloudinary.com/dptznozxq/image/upload/v1776320381/tryon/linesheet/MRS-SS-25.png",
    "clean_url": "https://res.cloudinary.com/dptznozxq/image/upload/v1776320382/tryon/linesheet_clean/MRS-SS-25_clean.png"
  },
  {
    "sku": "PXL-SS-25",
    "name": "PIXEL PANTS",
    "mrp": 8500.0,
    "color": "blue",
    "fabric": "MILL DEADSTOCK  10.5  OUNCE    100% COTTON LYCRA DENIM",
    "description": "high waisted - top stitch detail -  round front pocket - back patch pocket -front fly closure- narrow pant leg - ankle length",
    "category": "bottoms",
    "sub_category": "pants",
    "occasion": "work, vacation, party",
    "style_vibe": "statement",
    "color_family": "pastels",
    "silhouette": "tailored",
    "body_types": "",
    "fit_note": "true-to-size",
    "pairs_with": "",
    "avoid_pairing": "",
    "styling_note": "",
    "bestseller": "",
    "season": "",
    "image_file": "PXL-SS-25.png",
    "has_image": true,
    "image_file_clean": "PXL-SS-25_clean.png",
    "shopify_image": "PXL-SS-25_shopify.jpg",
    "shopify_url": "https://cdn.shopify.com/s/files/1/0635/1791/7437/files/ASV09092.jpg?v=1749886025&width=1946",
    "image_file_shopify": "PXL-SS-25_shopify.jpg",
    "has_shopify": true,
    "shopify_clean": "PXL-SS-25_shopify_clean.png",
    "linesheet_image": "PXL-SS-25.png",
    "linesheet_clean": "PXL-SS-25_clean.png",
    "display_url": "https://res.cloudinary.com/dptznozxq/image/upload/v1776320384/tryon/linesheet/PXL-SS-25.png",
    "clean_url": "https://res.cloudinary.com/dptznozxq/image/upload/v1776320385/tryon/linesheet_clean/PXL-SS-25_clean.png"
  },
  {
    "sku": "EST-SS-25",
    "name": "ESCAPE TOP",
    "mrp": 5000.0,
    "color": "blue and grey",
    "fabric": "100% COTTON GINGHAM CHECK WEAVE",
    "description": "v shape neckline - pleat gathers - flared fit - short length",
    "category": "tops",
    "sub_category": "top",
    "occasion": "vacation",
    "style_vibe": "playful",
    "color_family": "pastels",
    "silhouette": "tailored",
    "body_types": "",
    "fit_note": "true-to-size",
    "pairs_with": "",
    "avoid_pairing": "",
    "styling_note": "",
    "bestseller": "",
    "season": "",
    "image_file": "EST-SS-25.png",
    "has_image": true,
    "image_file_clean": "EST-SS-25_clean.png",
    "shopify_image": "EST-SS-25_shopify.jpg",
    "shopify_url": "https://cdn.shopify.com/s/files/1/0635/1791/7437/files/ASV08201-2.jpg?v=1776170860&width=1946",
    "image_file_shopify": "EST-SS-25_shopify.jpg",
    "has_shopify": true,
    "shopify_clean": "EST-SS-25_shopify_clean.png",
    "linesheet_image": "EST-SS-25.png",
    "linesheet_clean": "EST-SS-25_clean.png",
    "display_url": "https://res.cloudinary.com/dptznozxq/image/upload/v1776320386/tryon/linesheet/EST-SS-25.png",
    "clean_url": "https://res.cloudinary.com/dptznozxq/image/upload/v1776320387/tryon/linesheet_clean/EST-SS-25_clean.png"
  },
  {
    "sku": "ESP-SS-25",
    "name": "ESCAPE PANT",
    "mrp": 6000.0,
    "color": "blue and grey",
    "fabric": "100% COTTON GINGHAM CHECK WEAVE",
    "description": "high waisted - front fly closure - side pockets - straight pant leg",
    "category": "bottoms",
    "sub_category": "pants",
    "occasion": "vacation, casual",
    "style_vibe": "playful",
    "color_family": "pastels",
    "silhouette": "relaxed",
    "body_types": "",
    "fit_note": "true-to-size",
    "pairs_with": "",
    "avoid_pairing": "",
    "styling_note": "",
    "bestseller": "",
    "season": "",
    "image_file": "ESP-SS-25.png",
    "has_image": true,
    "image_file_clean": "ESP-SS-25_clean.png",
    "shopify_image": "ESP-SS-25_shopify.jpg",
    "shopify_url": "https://cdn.shopify.com/s/files/1/0635/1791/7437/files/ASV08190_d061257b-25f8-4a8c-96cc-aa1810882aae.jpg?v=1776170860&width=1946",
    "image_file_shopify": "ESP-SS-25_shopify.jpg",
    "has_shopify": true,
    "shopify_clean": "ESP-SS-25_shopify_clean.png",
    "linesheet_image": "ESP-SS-25.png",
    "linesheet_clean": "ESP-SS-25_clean.png",
    "display_url": "https://res.cloudinary.com/dptznozxq/image/upload/v1776320389/tryon/linesheet/ESP-SS-25.png",
    "clean_url": "https://res.cloudinary.com/dptznozxq/image/upload/v1776320390/tryon/linesheet_clean/ESP-SS-25_clean.png"
  },
  {
    "sku": "ESS-SS-25",
    "name": "ESCAPE SET",
    "mrp": 10500.0,
    "color": "blue and grey",
    "fabric": "100% COTTON GINGHAM CHECK WEAVE",
    "description": "",
    "category": "sets",
    "sub_category": "co-ord",
    "occasion": "vacation",
    "style_vibe": "playful",
    "color_family": "pastels",
    "silhouette": "relaxed",
    "body_types": "",
    "fit_note": "true-to-size",
    "pairs_with": "",
    "avoid_pairing": "",
    "styling_note": "",
    "bestseller": "",
    "season": "",
    "image_file": "ESS-SS-25.png",
    "has_image": true,
    "image_file_clean": "ESS-SS-25_clean.png",
    "shopify_image": "ESS-SS-25_shopify.jpg",
    "shopify_url": "https://cdn.shopify.com/s/files/1/0635/1791/7437/files/ESCAPE_SET_SS25.png?v=1776170860&width=1946",
    "image_file_shopify": "ESS-SS-25_shopify.jpg",
    "has_shopify": true,
    "shopify_clean": "ESS-SS-25_shopify_clean.png",
    "linesheet_image": ""
  },
  {
    "sku": "DCV-SS-25",
    "name": "DECCAN VEST",
    "mrp": 7250.0,
    "color": "electric blue",
    "fabric": "100% COTTON WINDOWPANE CHECK WEAVE",
    "description": "boat neck detail - short shoulder straps - front button closure - fitted on the waist - regular top length",
    "category": "tops",
    "sub_category": "vest",
    "occasion": "vacation, work",
    "style_vibe": "elegant",
    "color_family": "jewel",
    "silhouette": "tailored",
    "body_types": "",
    "fit_note": "true-to-size",
    "pairs_with": "",
    "avoid_pairing": "",
    "styling_note": "",
    "bestseller": "",
    "season": "",
    "image_file": "",
    "has_image": false,
    "shopify_image": "DCV-SS-25_shopify.jpg",
    "shopify_url": "https://cdn.shopify.com/s/files/1/0635/1791/7437/files/DECCAN_VEST.png?v=1776169801&width=1946",
    "image_file_shopify": "DCV-SS-25_shopify.jpg",
    "has_shopify": true,
    "shopify_clean": "DCV-SS-25_shopify_clean.png",
    "linesheet_image": "DCV-SS-25.jpg",
    "linesheet_clean": "DCV-SS-25_clean.png",
    "display_url": "https://res.cloudinary.com/dptznozxq/image/upload/v1776320392/tryon/linesheet/DCV-SS-25.jpg",
    "clean_url": "https://res.cloudinary.com/dptznozxq/image/upload/v1776320397/tryon/linesheet_clean/DCV-SS-25_clean.png"
  },
  {
    "sku": "PDS-SS-25",
    "name": "PROMENADE SHORTS",
    "mrp": 5000.0,
    "color": "white",
    "fabric": "MILL DEADSTOCK  10.5 OUNCE    100% COTTON  LYCRA DENIM",
    "description": "high waist - front fly closure - front and back pleat detail - front side pockets - front fly closure - back patch pocket - mid thigh length",
    "category": "bottoms",
    "sub_category": "shorts",
    "occasion": "casual, vacation",
    "style_vibe": "classic",
    "color_family": "neutrals",
    "silhouette": "relaxed",
    "body_types": "",
    "fit_note": "true-to-size",
    "pairs_with": "",
    "avoid_pairing": "",
    "styling_note": "",
    "bestseller": "",
    "season": "",
    "image_file": "PDS-SS-25.png",
    "has_image": true,
    "image_file_clean": "PDS-SS-25_clean.png",
    "shopify_image": "PDS-SS-25_shopify.jpg",
    "shopify_url": "https://cdn.shopify.com/s/files/1/0635/1791/7437/files/PROMANADE_SHORTS.png?v=1776171473&width=1946",
    "image_file_shopify": "PDS-SS-25_shopify.jpg",
    "has_shopify": true,
    "shopify_clean": "PDS-SS-25_shopify_clean.png",
    "linesheet_image": "PDS-SS-25.jpg",
    "linesheet_clean": "PDS-SS-25_clean.png",
    "display_url": "https://res.cloudinary.com/dptznozxq/image/upload/v1776320398/tryon/linesheet/PDS-SS-25.jpg",
    "clean_url": "https://res.cloudinary.com/dptznozxq/image/upload/v1776320402/tryon/linesheet_clean/PDS-SS-25_clean.png"
  },
  {
    "sku": "RPS-SS-25",
    "name": "RIPPLE SHIRT (SAGE)",
    "mrp": 8500.0,
    "color": "sage",
    "fabric": "DEAD STOCK COTTON POPLIN",
    "description": "notched collar - shoulder to arm ruching detail - regular cuff - high to low hem - relaxed fit",
    "category": "tops",
    "sub_category": "shirt",
    "occasion": "vacation, work",
    "style_vibe": "elegant",
    "color_family": "pastels",
    "silhouette": "tailored",
    "body_types": "",
    "fit_note": "true-to-size",
    "pairs_with": "",
    "avoid_pairing": "",
    "styling_note": "",
    "bestseller": "",
    "season": "",
    "image_file": "RPS-SS-25.jpg",
    "has_image": true,
    "image_file_clean": "RPS-SS-25_clean.png",
    "shopify_image": "RPS-SS-25_shopify.jpg",
    "shopify_url": "https://cdn.shopify.com/s/files/1/0635/1791/7437/files/ASV08924-3.jpg?v=1750420320&width=1946",
    "image_file_shopify": "RPS-SS-25_shopify.jpg",
    "has_shopify": true,
    "shopify_clean": "RPS-SS-25_shopify_clean.png",
    "linesheet_image": "RPS-SS-25.png",
    "linesheet_clean": "RPS-SS-25_clean.png",
    "display_url": "https://res.cloudinary.com/dptznozxq/image/upload/v1776320366/tryon/linesheet/RPS-SS-25.png",
    "clean_url": "https://res.cloudinary.com/dptznozxq/image/upload/v1776320368/tryon/linesheet_clean/RPS-SS-25_clean.png"
  },
  {
    "sku": "CTS-SS-25",
    "name": "CITRON SHIRT",
    "mrp": 6500.0,
    "color": "beige , butter yellow",
    "fabric": "RECYCLED COTTON KNIT",
    "description": "polo neck - front button closure - shoulder and back pleat detail - contrast collar and button detail - slim fit",
    "category": "tops",
    "sub_category": "shirt",
    "occasion": "vacation, work",
    "style_vibe": "classic",
    "color_family": "pastels",
    "silhouette": "relaxed",
    "body_types": "",
    "fit_note": "runs-small",
    "pairs_with": "",
    "avoid_pairing": "",
    "styling_note": "",
    "bestseller": "",
    "season": "",
    "image_file": "CTS-SS-25.png",
    "has_image": true,
    "image_file_clean": "CTS-SS-25_clean.png",
    "shopify_image": "CTS-SS-25_shopify.jpg",
    "shopify_url": "https://cdn.shopify.com/s/files/1/0635/1791/7437/files/ASV08168_d5f61eeb-48b5-4ab9-ab67-0ef293727779.jpg?v=1750766416&width=1946",
    "image_file_shopify": "CTS-SS-25_shopify.jpg",
    "has_shopify": true,
    "shopify_clean": "CTS-SS-25_shopify_clean.png",
    "linesheet_image": "CTS-SS-25.jpg",
    "linesheet_clean": "CTS-SS-25_clean.png",
    "display_url": "https://res.cloudinary.com/dptznozxq/image/upload/v1776320405/tryon/linesheet/CTS-SS-25.jpg",
    "clean_url": "https://res.cloudinary.com/dptznozxq/image/upload/v1776320408/tryon/linesheet_clean/CTS-SS-25_clean.png"
  },
  {
    "sku": "STS-SS-25",
    "name": "STRIA SHIRT",
    "mrp": 12000.0,
    "color": "white",
    "fabric": "MILL DEADSTOCK                       5.5 OUNCE  100% COTTON    RFD DENIM",
    "description": "open collar - front button closure - frayed fabric strip detail - regular cuff - relaxed fit",
    "category": "tops",
    "sub_category": "shirt",
    "occasion": "vacation, party, evening, wedding",
    "style_vibe": "elegant",
    "color_family": "monochrome",
    "silhouette": "relaxed",
    "body_types": "",
    "fit_note": "true-to-size",
    "pairs_with": "",
    "avoid_pairing": "",
    "styling_note": "",
    "bestseller": "",
    "season": "",
    "image_file": "STS-SS-25.jpg",
    "has_image": true,
    "image_file_clean": "STS-SS-25_clean.png",
    "shopify_image": "STS-SS-25_shopify.jpg",
    "shopify_url": "https://cdn.shopify.com/s/files/1/0635/1791/7437/files/ASV09086_621c03c5-6ace-4ce9-890f-fa31c4254238.jpg?v=1750767394&width=1946",
    "image_file_shopify": "STS-SS-25_shopify.jpg",
    "has_shopify": true,
    "shopify_clean": "STS-SS-25_shopify_clean.png",
    "linesheet_image": "STS-SS-25.png",
    "linesheet_clean": "STS-SS-25_clean.png",
    "display_url": "https://res.cloudinary.com/dptznozxq/image/upload/v1776320409/tryon/linesheet/STS-SS-25.png",
    "clean_url": "https://res.cloudinary.com/dptznozxq/image/upload/v1776320410/tryon/linesheet_clean/STS-SS-25_clean.png"
  },
  {
    "sku": "SRS-SS-25",
    "name": "SAHARA SHIRT",
    "mrp": 12000.0,
    "color": "blue",
    "fabric": "MILL DEADSTOCK  7.5  OUNCE 100%   COTTON DENIM",
    "description": "open collar - front button closure - fabric scrap flower detail - regular cuff- relaxed fit",
    "category": "tops",
    "sub_category": "shirt",
    "occasion": "vacation, party, evening, wedding",
    "style_vibe": "statement",
    "color_family": "jewel",
    "silhouette": "relaxed",
    "body_types": "",
    "fit_note": "runs-large",
    "pairs_with": "",
    "avoid_pairing": "",
    "styling_note": "",
    "bestseller": "",
    "season": "",
    "image_file": "SRS-SS-25.jpg",
    "has_image": true,
    "image_file_clean": "SRS-SS-25_clean.png",
    "shopify_image": "SRS-SS-25_shopify.jpg",
    "shopify_url": "https://cdn.shopify.com/s/files/1/0635/1791/7437/files/ASV08310_5fa22c16-35b2-4f00-bfc1-dce74ffc4864.jpg?v=1750762671&width=1946",
    "image_file_shopify": "SRS-SS-25_shopify.jpg",
    "has_shopify": true,
    "shopify_clean": "SRS-SS-25_shopify_clean.png",
    "linesheet_image": "SRS-SS-25.png",
    "linesheet_clean": "SRS-SS-25_clean.png",
    "display_url": "https://res.cloudinary.com/dptznozxq/image/upload/v1776320412/tryon/linesheet/SRS-SS-25.png",
    "clean_url": "https://res.cloudinary.com/dptznozxq/image/upload/v1776320413/tryon/linesheet_clean/SRS-SS-25_clean.png"
  },
  {
    "sku": "AVC-SS-25",
    "name": "AVENUE VEST (CRIMSON)",
    "mrp": 6000.0,
    "color": "crimson",
    "fabric": "MILL DEADSTOCK  7.5  OUNCE 100%   COTTON DENIM",
    "description": "drop shoulder - neck and armhole ribbing - front and backoverlock strip detail - relaxed  fit",
    "category": "tops",
    "sub_category": "vest",
    "occasion": "vacation, casual",
    "style_vibe": "playful",
    "color_family": "bright",
    "silhouette": "relaxed",
    "body_types": "",
    "fit_note": "runs-large",
    "pairs_with": "",
    "avoid_pairing": "",
    "styling_note": "",
    "bestseller": "",
    "season": "",
    "image_file": "AVC-SS-25.jpg",
    "has_image": true,
    "image_file_clean": "AVC-SS-25_clean.png",
    "shopify_image": "AVC-SS-25_shopify.jpg",
    "shopify_url": "https://cdn.shopify.com/s/files/1/0635/1791/7437/files/ASV08135-2.jpg?v=1768893854&width=1946",
    "image_file_shopify": "AVC-SS-25_shopify.jpg",
    "has_shopify": true,
    "shopify_clean": "AVC-SS-25_shopify_clean.png",
    "linesheet_image": "AVC-SS-25.png",
    "linesheet_clean": "AVC-SS-25_clean.png",
    "display_url": "https://res.cloudinary.com/dptznozxq/image/upload/v1776320414/tryon/linesheet/AVC-SS-25.png",
    "clean_url": "https://res.cloudinary.com/dptznozxq/image/upload/v1776320415/tryon/linesheet_clean/AVC-SS-25_clean.png"
  },
  {
    "sku": "AVL-SS-25",
    "name": "AVENUE VEST (PALE LIME)",
    "mrp": 6000.0,
    "color": "pale lime",
    "fabric": "SINGLE JERSEY 100% RECYCLED COTTON",
    "description": "drop shoulder - neck and armhole ribbing - front and back overlock strip detail - relaxed  fit",
    "category": "tops",
    "sub_category": "vest",
    "occasion": "vacation, casual",
    "style_vibe": "playful",
    "color_family": "bright",
    "silhouette": "relaxed",
    "body_types": "",
    "fit_note": "runs-large",
    "pairs_with": "",
    "avoid_pairing": "",
    "styling_note": "",
    "bestseller": "",
    "season": "",
    "image_file": "AVL-SS-25.png",
    "has_image": true,
    "image_file_clean": "AVL-SS-25_clean.png",
    "shopify_image": "AVL-SS-25_shopify.jpg",
    "shopify_url": "https://cdn.shopify.com/s/files/1/0635/1791/7437/files/ASV08119_f261d58c-dcd9-4fb3-9834-ca8fc6043d78.jpg?v=1768893864&width=1946",
    "image_file_shopify": "AVL-SS-25_shopify.jpg",
    "has_shopify": true,
    "shopify_clean": "AVL-SS-25_shopify_clean.png",
    "linesheet_image": "AVL-SS-25.png",
    "linesheet_clean": "AVL-SS-25_clean.png",
    "display_url": "https://res.cloudinary.com/dptznozxq/image/upload/v1776320416/tryon/linesheet/AVL-SS-25.png",
    "clean_url": "https://res.cloudinary.com/dptznozxq/image/upload/v1776320418/tryon/linesheet_clean/AVL-SS-25_clean.png"
  },
  {
    "sku": "SFV-SS-25",
    "name": "SAFARI VEST",
    "mrp": 6000.0,
    "color": "beige, blue",
    "fabric": "SINGLE JERSEY 100% RECYCLED COTTON",
    "description": "drop shoulder - rolled seam detail - relaxed fit",
    "category": "tops",
    "sub_category": "vest",
    "occasion": "vacation, casual",
    "style_vibe": "classic",
    "color_family": "neutrals",
    "silhouette": "relaxed",
    "body_types": "",
    "fit_note": "runs-large",
    "pairs_with": "",
    "avoid_pairing": "",
    "styling_note": "",
    "bestseller": "",
    "season": "",
    "image_file": "SFV-SS-25.png",
    "has_image": true,
    "image_file_clean": "SFV-SS-25_clean.png",
    "has_shopify": false,
    "linesheet_image": "SFV-SS-25.png",
    "linesheet_clean": "SFV-SS-25_clean.png",
    "display_url": "https://res.cloudinary.com/dptznozxq/image/upload/v1776320419/tryon/linesheet/SFV-SS-25.png",
    "clean_url": "https://res.cloudinary.com/dptznozxq/image/upload/v1776320420/tryon/linesheet_clean/SFV-SS-25_clean.png"
  },
  {
    "sku": "CTJ-SS-25",
    "name": "CONTOUR JEANS",
    "mrp": 10000.0,
    "color": "blue",
    "fabric": "MILL DEADSTOCK  10.5 OUNCE 100% COTTON DENIM",
    "description": "concealed waist line - front fly closure - front side pocket - back patch pocket -structured panel detail -  oversized pant leg",
    "category": "bottoms",
    "sub_category": "jeans",
    "occasion": "vacation, party",
    "style_vibe": "statement",
    "color_family": "jewel",
    "silhouette": "relaxed",
    "body_types": "",
    "fit_note": "true-to-size",
    "pairs_with": "",
    "avoid_pairing": "",
    "styling_note": "",
    "bestseller": "",
    "season": "",
    "image_file": "CTJ-SS-25.png",
    "has_image": true,
    "image_file_clean": "CTJ-SS-25_clean.png",
    "shopify_image": "CTJ-SS-25_shopify.jpg",
    "shopify_url": "https://cdn.shopify.com/s/files/1/0635/1791/7437/files/ASV08706-2.jpg?v=1750837139&width=1946",
    "image_file_shopify": "CTJ-SS-25_shopify.jpg",
    "has_shopify": true,
    "shopify_clean": "CTJ-SS-25_shopify_clean.png",
    "linesheet_image": "CTJ-SS-25.png",
    "linesheet_clean": "CTJ-SS-25_clean.png",
    "display_url": "https://res.cloudinary.com/dptznozxq/image/upload/v1776320421/tryon/linesheet/CTJ-SS-25.png",
    "clean_url": "https://res.cloudinary.com/dptznozxq/image/upload/v1776320422/tryon/linesheet_clean/CTJ-SS-25_clean.png"
  },
  {
    "sku": "SFS-SS-25",
    "name": "SAFARI SHIRT",
    "mrp": 8500.0,
    "color": "beige",
    "fabric": "MILL DEADSTOCK 4.5 OUNCE   100% COTTON DENIM  + MILL DEADSTOCK   5.5 OUNCE RFD DENIM",
    "description": "open collar - front button closure -  front welt pocket detail -contrast panel - regular cuff - relaxed fit",
    "category": "tops",
    "sub_category": "shirt",
    "occasion": "vacation, party",
    "style_vibe": "elegant",
    "color_family": "pastels",
    "silhouette": "relaxed",
    "body_types": "",
    "fit_note": "true-to-size",
    "pairs_with": "",
    "avoid_pairing": "",
    "styling_note": "",
    "bestseller": "",
    "season": "",
    "image_file": "SFS-SS-25.png",
    "has_image": true,
    "image_file_clean": "SFS-SS-25_clean.png",
    "shopify_image": "SFS-SS-25_shopify.jpg",
    "shopify_url": "https://cdn.shopify.com/s/files/1/0635/1791/7437/files/ASV08685-2.jpg?v=1750836337&width=1946",
    "image_file_shopify": "SFS-SS-25_shopify.jpg",
    "has_shopify": true,
    "shopify_clean": "SFS-SS-25_shopify_clean.png",
    "linesheet_image": "SFS-SS-25.png",
    "linesheet_clean": "SFS-SS-25_clean.png",
    "display_url": "https://res.cloudinary.com/dptznozxq/image/upload/v1776320423/tryon/linesheet/SFS-SS-25.png",
    "clean_url": "https://res.cloudinary.com/dptznozxq/image/upload/v1776320424/tryon/linesheet_clean/SFS-SS-25_clean.png"
  },
  {
    "sku": "KMS-SS-25",
    "name": "KALAMATA SHIRT",
    "mrp": 7000.0,
    "color": "black and grey",
    "fabric": "100% COTTON TARTAN CHECK WEAVE + MILL DEADSTOCK 5 OUNCE 100% COTTON DENIM",
    "description": "regular collar - front button closure - front patch pocket - raglan sleeve - folded hem detail - regular fit",
    "category": "tops",
    "sub_category": "shirt",
    "occasion": "vacation, party, casual ",
    "style_vibe": "classic",
    "color_family": "monochrome",
    "silhouette": "relaxed",
    "body_types": "",
    "fit_note": "true-to-size",
    "pairs_with": "",
    "avoid_pairing": "",
    "styling_note": "",
    "bestseller": "",
    "season": "",
    "image_file": "KMS-SS-25.png",
    "has_image": true,
    "image_file_clean": "KMS-SS-25_clean.png",
    "shopify_image": "KMS-SS-25_shopify.jpg",
    "shopify_url": "https://cdn.shopify.com/s/files/1/0635/1791/7437/files/ASV08505-2.jpg?v=1750832396&width=1946",
    "image_file_shopify": "KMS-SS-25_shopify.jpg",
    "has_shopify": true,
    "shopify_clean": "KMS-SS-25_shopify_clean.png",
    "linesheet_image": "KMS-SS-25.png",
    "linesheet_clean": "KMS-SS-25_clean.png",
    "display_url": "https://res.cloudinary.com/dptznozxq/image/upload/v1776320425/tryon/linesheet/KMS-SS-25.png",
    "clean_url": "https://res.cloudinary.com/dptznozxq/image/upload/v1776320426/tryon/linesheet_clean/KMS-SS-25_clean.png"
  },
  {
    "sku": "RYP-SS-25",
    "name": "RAYA PANTS",
    "mrp": 10000.0,
    "color": "black",
    "fabric": "MILL DEADSTOCK  12 OUNCE  100%   COTTON DENIM",
    "description": "regular waist -  front side pocket - back patch pocket - front pleat detail -front fly closure- embroidered strap detail - relaxed pant leg",
    "category": "bottoms",
    "sub_category": "pants",
    "occasion": "vacation, party, evening, wedding",
    "style_vibe": "elegant",
    "color_family": "monochrome",
    "silhouette": "relaxed",
    "body_types": "",
    "fit_note": "true-to-size",
    "pairs_with": "",
    "avoid_pairing": "",
    "styling_note": "",
    "bestseller": "",
    "season": "",
    "image_file": "RYP-SS-25.png",
    "has_image": true,
    "image_file_clean": "RYP-SS-25_clean.png",
    "has_shopify": false,
    "linesheet_image": "RYP-SS-25.png",
    "linesheet_clean": "RYP-SS-25_clean.png",
    "display_url": "https://res.cloudinary.com/dptznozxq/image/upload/v1776320427/tryon/linesheet/RYP-SS-25.png",
    "clean_url": "https://res.cloudinary.com/dptznozxq/image/upload/v1776320428/tryon/linesheet_clean/RYP-SS-25_clean.png"
  },
  {
    "sku": "DFS-SS-25",
    "name": "DRIFT SHIRT",
    "mrp": 8500.0,
    "color": "grey,green",
    "fabric": "100%  COTTON TARTAN CHECK WEAVE",
    "description": "open collar - drop shoulder - front button closure - fabric loop detail -regular cuff - relaxed fit",
    "category": "tops",
    "sub_category": "shirt",
    "occasion": "vacation, party, evening",
    "style_vibe": "elegant",
    "color_family": "pastels",
    "silhouette": "relaxed",
    "body_types": "",
    "fit_note": "true-to-size",
    "pairs_with": "",
    "avoid_pairing": "",
    "styling_note": "",
    "bestseller": "",
    "season": "",
    "image_file": "DFS-SS-25.png",
    "has_image": true,
    "image_file_clean": "DFS-SS-25_clean.png",
    "shopify_image": "DFS-SS-25_shopify.jpg",
    "shopify_url": "https://cdn.shopify.com/s/files/1/0635/1791/7437/files/ASV08609_2a393c97-e19f-425d-ad94-44d760d678e1.jpg?v=1750768390&width=1946",
    "image_file_shopify": "DFS-SS-25_shopify.jpg",
    "has_shopify": true,
    "shopify_clean": "DFS-SS-25_shopify_clean.png",
    "linesheet_image": "DFS-SS-25.png",
    "linesheet_clean": "DFS-SS-25_clean.png",
    "display_url": "https://res.cloudinary.com/dptznozxq/image/upload/v1776320429/tryon/linesheet/DFS-SS-25.png",
    "clean_url": "https://res.cloudinary.com/dptznozxq/image/upload/v1776320430/tryon/linesheet_clean/DFS-SS-25_clean.png"
  }
]